{
  "exportSchemaVersion": 1,
  "parserVersion": "2026-03-19-durable-normalization-v1",
  "source": {
    "url": "http://wahapedia.ru/wh40k10ed/factions/astra-militarum/Death-Korps-Grenadier-Squad",
    "normalizedUrl": "http://wahapedia.ru/wh40k10ed/factions/astra-militarum/Death-Korps-Grenadier-Squad",
    "canonicalSourceId": "wahapedia:85e4905af3b2b0b14ed9355d77c6c6cbcae9cfdd",
    "faction_slug": "astra-militarum",
    "datasheet_slug": "Death-Korps-Grenadier-Squad",
    "fetchedAt": "2026-03-19T17:12:12+00:00",
    "contentHash": "af83cbf3cc97cf742fd5430ea7d5f2c7c35ec13f6cf009a30fd587410e6092e3",
    "output_slug": "astra-militarum"
  },
  "name": "Death Korps Grenadier Squad",
  "base_size": "",
  "characteristics": {
    "M": "6\"",
    "T": "3",
    "Sv": "4+",
    "W": "1",
    "Ld": "7+",
    "OC": "2"
  },
  "weapons": {
    "ranged_weapons": [
      {
        "name": "Flamer",
        "abilities": [
          "ignores cover",
          "torrent"
        ],
        "range": "12\"",
        "a": "D6",
        "bs": "N/A",
        "s": "4",
        "ap": "0",
        "d": "1"
      },
      {
        "name": "Grenade launcher \u2013 frag",
        "abilities": [
          "blast"
        ],
        "range": "24\"",
        "a": "D3",
        "bs": "3+",
        "s": "4",
        "ap": "0",
        "d": "1"
      },
      {
        "name": "Grenade launcher \u2013 krak",
        "abilities": [],
        "range": "24\"",
        "a": "1",
        "bs": "3+",
        "s": "9",
        "ap": "-2",
        "d": "D3"
      },
      {
        "name": "Heavy flamer",
        "abilities": [
          "ignores cover",
          "torrent"
        ],
        "range": "12\"",
        "a": "D6",
        "bs": "N/A",
        "s": "5",
        "ap": "-1",
        "d": "1"
      },
      {
        "name": "Heavy stubber",
        "abilities": [
          "heavy",
          "rapid fire 3"
        ],
        "range": "36\"",
        "a": "3",
        "bs": "4+",
        "s": "4",
        "ap": "0",
        "d": "1"
      },
      {
        "name": "Hot-shot lasgun",
        "abilities": [
          "rapid fire 1"
        ],
        "range": "24\"",
        "a": "1",
        "bs": "3+",
        "s": "3",
        "ap": "-1",
        "d": "1"
      },
      {
        "name": "Meltagun",
        "abilities": [
          "melta 2"
        ],
        "range": "12\"",
        "a": "1",
        "bs": "3+",
        "s": "9",
        "ap": "-4",
        "d": "D6"
      },
      {
        "name": "Plasma gun \u2013 standard",
        "abilities": [
          "rapid fire 1"
        ],
        "range": "24\"",
        "a": "1",
        "bs": "3+",
        "s": "7",
        "ap": "-2",
        "d": "1"
      },
      {
        "name": "Plasma gun \u2013 supercharge",
        "abilities": [
          "hazardous",
          "rapid fire 1"
        ],
        "range": "24\"",
        "a": "1",
        "bs": "3+",
        "s": "8",
        "ap": "-3",
        "d": "2"
      },
      {
        "name": "Sergeant\u2019s pistol",
        "abilities": [
          "pistol"
        ],
        "range": "12\"",
        "a": "1",
        "bs": "3+",
        "s": "3",
        "ap": "-1",
        "d": "1"
      },
      {
        "name": "Sniper rifle",
        "abilities": [
          "heavy",
          "precision"
        ],
        "range": "36\"",
        "a": "1",
        "bs": "3+",
        "s": "4",
        "ap": "-2",
        "d": "2"
      }
    ],
    "melee_weapons": [
      {
        "name": "Close combat weapon",
        "abilities": [],
        "range": "Melee",
        "a": "1",
        "ws": "4+",
        "s": "3",
        "ap": "0",
        "d": "1"
      },
      {
        "name": "Sergeant\u2019s close combat weapon",
        "abilities": [],
        "range": "Melee",
        "a": "2",
        "ws": "4+",
        "s": "4",
        "ap": "-2",
        "d": "1"
      }
    ]
  },
  "abilities": {
    "core": [],
    "faction": [],
    "datasheet": [],
    "other": [
      {
        "type": "text",
        "text": "Primed and Ready: In your Shooting phase , you can select one unit from your army with this ability as the target of the Grenade Stratagem for 0CP, provided that unit has not already been the target of that Stratagem this phase. This can allow you to use the Grenade Stratagem for a second time this phase."
      }
    ]
  },
  "unit_composition": [
    {
      "type": "points",
      "rows": [
        {
          "label": "10 models",
          "points": "110"
        }
      ]
    }
  ],
  "keywords": [
    "INFANTRY",
    "IMPERIUM",
    "GRENADES",
    "REGIMENT",
    "PLATOON",
    "DEATH KORPS GRENADIER SQUAD"
  ],
  "faction_keywords": [
    "ASTRA MILITARUM"
  ],
  "sections": [
    {
      "title": "WARGEAR OPTIONS",
      "entries": [
        {
          "type": "option_group",
          "label": "Up to 2 Grenadier models can each have their hot-shot lasgun replaced with one of the following:",
          "items": [
            "1 flamer",
            "1 grenade launcher",
            "1 heavy stubber",
            "1 meltagun",
            "1 plasma gun",
            "1 sniper rifle"
          ]
        }
      ]
    },
    {
      "title": "ABILITIES",
      "entries": [
        {
          "type": "text",
          "text": "Primed and Ready: In your Shooting phase , you can select one unit from your army with this ability as the target of the Grenade Stratagem for 0CP, provided that unit has not already been the target of that Stratagem this phase. This can allow you to use the Grenade Stratagem for a second time this phase."
        }
      ]
    },
    {
      "title": "WARGEAR ABILITIES",
      "entries": [
        {
          "type": "text",
          "text": "Vox-caster: Each time you target the bearer\u2019s unit with a Stratagem , roll one D6, adding 1 to the result if there are one or more friendly OFFICER models within 6\": on a 5+, you gain 1CP."
        }
      ]
    },
    {
      "title": "UNIT COMPOSITION",
      "entries": [
        {
          "type": "points",
          "rows": [
            {
              "label": "10 models",
              "points": "110"
            }
          ]
        }
      ]
    },
    {
      "title": "GRENADIER SQUAD",
      "entries": [
        {
          "type": "text",
          "text": "If a model from your army with the Leader ability can be attached to a DEATH KORPS OF KRIEG unit, it can be attached to this unit instead."
        }
      ]
    }
  ],
  "quality": {
    "rawSectionTitles": [
      "RANGED WEAPONS",
      "RANGE",
      "A",
      "BS",
      "S",
      "AP",
      "D",
      "MELEE WEAPONS",
      "RANGE",
      "A",
      "WS",
      "S",
      "AP",
      "D",
      "WARGEAR OPTIONS",
      "ABILITIES",
      "WARGEAR ABILITIES",
      "UNIT COMPOSITION",
      "GRENADIER SQUAD",
      "STRATAGEMS",
      "LED BY",
      "DETACHMENT ABILITY"
    ],
    "exportedSectionTitles": [
      "WARGEAR OPTIONS",
      "ABILITIES",
      "WARGEAR ABILITIES",
      "UNIT COMPOSITION",
      "GRENADIER SQUAD"
    ],
    "missingExpectedSections": [
      "RANGED WEAPONS",
      "RANGE",
      "A",
      "BS",
      "S",
      "AP",
      "D",
      "MELEE WEAPONS",
      "RANGE",
      "A",
      "WS",
      "S",
      "AP",
      "D",
      "STRATAGEMS",
      "LED BY",
      "DETACHMENT ABILITY"
    ],
    "warnings": [
      "section-missing:RANGED WEAPONS",
      "section-missing:RANGE",
      "section-missing:A",
      "section-missing:BS",
      "section-missing:S",
      "section-missing:AP",
      "section-missing:D",
      "section-missing:MELEE WEAPONS",
      "section-missing:RANGE",
      "section-missing:A",
      "section-missing:WS",
      "section-missing:S",
      "section-missing:AP",
      "section-missing:D",
      "section-missing:STRATAGEMS",
      "section-missing:LED BY",
      "section-missing:DETACHMENT ABILITY",
      "section-missing:RANGED WEAPONS",
      "section-missing:RANGE",
      "section-missing:A",
      "section-missing:BS",
      "section-missing:S",
      "section-missing:AP",
      "section-missing:D",
      "section-missing:MELEE WEAPONS",
      "section-missing:RANGE",
      "section-missing:A",
      "section-missing:WS",
      "section-missing:S",
      "section-missing:AP",
      "section-missing:D",
      "section-missing:STRATAGEMS",
      "section-missing:LED BY",
      "section-missing:DETACHMENT ABILITY"
    ]
  }
}