{
  "exportSchemaVersion": 1,
  "parserVersion": "2026-03-20-builder-fidelity-v2",
  "source": {
    "url": "http://wahapedia.ru/wh40k10ed/factions/space-marines/Librarian-Dreadnought",
    "normalizedUrl": "http://wahapedia.ru/wh40k10ed/factions/space-marines/Librarian-Dreadnought",
    "canonicalSourceId": "wahapedia:99a516d26e859fb7a36344e999f49c52914831ac",
    "faction_slug": "space-marines",
    "datasheet_slug": "Librarian-Dreadnought",
    "fetchedAt": "2026-03-29T18:01:09+00:00",
    "contentHash": "69e37aee63cf93bf1ea4c4eeebf5a50317899e7507a83f724f4611d6c3d4a122",
    "output_slug": "blood-angels"
  },
  "name": "Librarian Dreadnought",
  "base_size": "\u230060mm",
  "characteristics": {
    "M": "8\"",
    "T": "9",
    "Sv": "2+",
    "W": "8",
    "Ld": "6+",
    "OC": "3"
  },
  "weapons": {
    "ranged_weapons": [
      {
        "name": "Blood Lance \u2013 witchfire",
        "abilities": [
          "psychic",
          "sustained hits d3"
        ],
        "range": "18\"",
        "a": "1",
        "bs": "3+",
        "s": "10",
        "ap": "-3",
        "d": "D6"
      },
      {
        "name": "Blood Lance \u2013 focused witchfire",
        "abilities": [
          "hazardous",
          "psychic",
          "sustained hits d3"
        ],
        "range": "18\"",
        "a": "1",
        "bs": "3+",
        "s": "12",
        "ap": "-3",
        "d": "D6+3"
      },
      {
        "name": "Heavy flamer",
        "abilities": [
          "ignores cover",
          "torrent"
        ],
        "range": "12\"",
        "a": "D6",
        "bs": "N/A",
        "s": "5",
        "ap": "-1",
        "d": "1"
      },
      {
        "name": "Meltagun",
        "abilities": [
          "melta 2"
        ],
        "range": "12\"",
        "a": "1",
        "bs": "3+",
        "s": "9",
        "ap": "-4",
        "d": "D6"
      },
      {
        "name": "Storm bolter",
        "abilities": [
          "rapid fire 2"
        ],
        "range": "24\"",
        "a": "2",
        "bs": "3+",
        "s": "4",
        "ap": "0",
        "d": "1"
      }
    ],
    "melee_weapons": [
      {
        "name": "Furioso fist",
        "abilities": [],
        "range": "Melee",
        "a": "5",
        "ws": "3+",
        "s": "12",
        "ap": "-3",
        "d": "3"
      },
      {
        "name": "Furioso force halberd",
        "abilities": [
          "extra attacks",
          "psychic"
        ],
        "range": "Melee",
        "a": "1",
        "ws": "2+",
        "s": "9",
        "ap": "-3",
        "d": "D6+3"
      }
    ]
  },
  "abilities": {
    "core": [
      "Deadly Demise 1"
    ],
    "faction": [
      "Oath of Moment"
    ],
    "datasheet": [
      {
        "type": "rule",
        "text": "While a friendly ADEPTUS ASTARTES unit is within 6\" of this model, models in that unit have the Feel No Pain 5+ ability against mortal wounds and Psychic Attacks .",
        "name": "Shield of Sanguinius (Aura, Psychic)"
      },
      {
        "type": "rule",
        "text": "Once per turn, at the end of your Movement phase , one PSYKER from your army with this ability can use it. If it does, roll one D6: on a 1, that PSYKER suffers D3 mortal wounds ; on a 2+, select one friendly ADEPTUS ASTARTES INFANTRY unit within 12\" of that PSYKER and remove the selected unit from the battlefield, then set it up again anywhere on the battlefield that is more than 9\" horizontally away from all enemy models.",
        "name": "Wings of Sanguinius (Psychic)"
      }
    ],
    "other": []
  },
  "unit_composition": [
    {
      "type": "list",
      "items": [
        "1 Librarian Dreadnought"
      ]
    },
    {
      "type": "statement",
      "text": "Blood Lance; storm bolter; Furioso fist, Furioso force halberd.",
      "label": "This model is equipped with"
    },
    {
      "type": "points",
      "rows": [
        {
          "label": "1 model",
          "points": "170"
        }
      ]
    }
  ],
  "keywords": [
    "VEHICLE",
    "WALKER",
    "SMOKE",
    "PSYKER",
    "IMPERIUM",
    "DREADNOUGHT",
    "LIBRARIAN DREADNOUGHT"
  ],
  "faction_keywords": [
    "ADEPTUS ASTARTES",
    "BLOOD ANGELS"
  ],
  "sections": [
    {
      "title": "WARGEAR OPTIONS",
      "entries": [
        {
          "type": "option_group",
          "label": "This model\u2019s storm bolter can be replaced with one of the following:",
          "items": [
            "1 heavy flamer",
            "1 meltagun"
          ]
        }
      ]
    },
    {
      "title": "ABILITIES",
      "entries": [
        {
          "type": "tagged_list",
          "label": "CORE",
          "items": [
            "Deadly Demise 1"
          ]
        },
        {
          "type": "tagged_list",
          "label": "FACTION",
          "items": [
            "Oath of Moment"
          ]
        },
        {
          "type": "rule",
          "text": "While a friendly ADEPTUS ASTARTES unit is within 6\" of this model, models in that unit have the Feel No Pain 5+ ability against mortal wounds and Psychic Attacks .",
          "name": "Shield of Sanguinius (Aura, Psychic)"
        },
        {
          "type": "rule",
          "text": "Once per turn, at the end of your Movement phase , one PSYKER from your army with this ability can use it. If it does, roll one D6: on a 1, that PSYKER suffers D3 mortal wounds ; on a 2+, select one friendly ADEPTUS ASTARTES INFANTRY unit within 12\" of that PSYKER and remove the selected unit from the battlefield, then set it up again anywhere on the battlefield that is more than 9\" horizontally away from all enemy models.",
          "name": "Wings of Sanguinius (Psychic)"
        }
      ]
    },
    {
      "title": "UNIT COMPOSITION",
      "entries": [
        {
          "type": "list",
          "items": [
            "1 Librarian Dreadnought"
          ]
        },
        {
          "type": "statement",
          "text": "Blood Lance; storm bolter; Furioso fist, Furioso force halberd.",
          "label": "This model is equipped with"
        },
        {
          "type": "points",
          "rows": [
            {
              "label": "1 model",
              "points": "170"
            }
          ]
        }
      ]
    }
  ],
  "quality": {
    "rawSectionTitles": [
      "WARGEAR OPTIONS",
      "ABILITIES",
      "UNIT COMPOSITION"
    ],
    "exportedSectionTitles": [
      "WARGEAR OPTIONS",
      "ABILITIES",
      "UNIT COMPOSITION"
    ],
    "missingExpectedSections": [],
    "warnings": [],
    "keywordColumnCount": 2
  }
}