{
  "source": {
    "url": "http://wahapedia.ru/wh40k10ed/factions/space-marines/Captain-Titus",
    "faction_slug": "space-marines",
    "datasheet_slug": "Captain-Titus",
    "output_slug": "ultramarines",
    "normalizedUrl": "http://wahapedia.ru/wh40k10ed/factions/space-marines/Captain-Titus",
    "canonicalSourceId": "wahapedia:2664a47ad8dfc7a20cdf995ed350a7955784dd02",
    "fetchedAt": "2026-03-19T17:35:02+00:00",
    "contentHash": "308dd59e218724096090d0243194644663ac62945267fe8f6cef4cadc4c0b008"
  },
  "name": "Captain Titus",
  "base_size": "\u230040mm",
  "characteristics": {
    "M": "6\"",
    "T": "4",
    "Sv": "3+",
    "W": "6",
    "Ld": "6+",
    "OC": "1",
    "Invulnerable Save": "4+"
  },
  "weapons": {
    "ranged_weapons": [
      {
        "name": "Bolt pistol",
        "abilities": [
          "PISTOL"
        ],
        "range": "12\"",
        "a": "1",
        "bs": "2+",
        "s": "4",
        "ap": "0",
        "d": "1"
      },
      {
        "name": "Master-crafted bolter",
        "abilities": [
          "assault",
          "heavy"
        ],
        "range": "24\"",
        "a": "2",
        "bs": "2+",
        "s": "4",
        "ap": "-1",
        "d": "2"
      }
    ],
    "melee_weapons": [
      {
        "name": "Master-crafted chainsword",
        "abilities": [
          "ANTI-INFANTRY 2+"
        ],
        "range": "Melee",
        "a": "8",
        "ws": "2+",
        "s": "5",
        "ap": "-1",
        "d": "2"
      }
    ]
  },
  "abilities": {
    "core": [
      "Feel No Pain 5+ , Leader"
    ],
    "faction": [
      "Oath of Moment"
    ],
    "datasheet": [
      {
        "type": "rule",
        "text": "Weapons equipped by models in this model\u2019s unit have the [SUSTAINED HITS 1] ability.",
        "name": "Press the Attack"
      },
      {
        "type": "rule",
        "text": "If this model is destroyed by a melee attack, if it has not fought this phase, roll one D6: on a 2+, do not remove it from play. This model can fight after the attacking unit has finished making its attacks. If one or more enemy models are destroyed as a result of those attacks, this model regains D3 lost wounds and is not destroyed; otherwise, it is removed from play.",
        "name": "Honour of Ultramar"
      }
    ],
    "other": []
  },
  "unit_composition": [
    {
      "type": "list",
      "items": [
        "1 Captain Titus \u2013 EPIC HERO"
      ]
    },
    {
      "type": "statement",
      "text": "bolt pistol; master-crafted bolter; master-crafted chainsword.",
      "label": "This model is equipped with"
    },
    {
      "type": "points",
      "rows": [
        {
          "label": "1 model",
          "points": "90"
        }
      ]
    }
  ],
  "keywords": [
    "INFANTRY",
    "CHARACTER",
    "EPIC HERO",
    "IMPERIUM",
    "TACTICUS",
    "GRENADES",
    "CAPTAIN",
    "TITUS"
  ],
  "faction_keywords": [
    "ADEPTUS ASTARTES",
    "ULTRAMARINES"
  ],
  "sections": [
    {
      "title": "ABILITIES",
      "entries": [
        {
          "type": "tagged_list",
          "label": "CORE",
          "items": [
            "Feel No Pain 5+ , Leader"
          ]
        },
        {
          "type": "tagged_list",
          "label": "FACTION",
          "items": [
            "Oath of Moment"
          ]
        },
        {
          "type": "rule",
          "text": "Weapons equipped by models in this model\u2019s unit have the [SUSTAINED HITS 1] ability.",
          "name": "Press the Attack"
        },
        {
          "type": "rule",
          "text": "If this model is destroyed by a melee attack, if it has not fought this phase, roll one D6: on a 2+, do not remove it from play. This model can fight after the attacking unit has finished making its attacks. If one or more enemy models are destroyed as a result of those attacks, this model regains D3 lost wounds and is not destroyed; otherwise, it is removed from play.",
          "name": "Honour of Ultramar"
        }
      ]
    },
    {
      "title": "UNIT COMPOSITION",
      "entries": [
        {
          "type": "list",
          "items": [
            "1 Captain Titus \u2013 EPIC HERO"
          ]
        },
        {
          "type": "statement",
          "text": "bolt pistol; master-crafted bolter; master-crafted chainsword.",
          "label": "This model is equipped with"
        },
        {
          "type": "points",
          "rows": [
            {
              "label": "1 model",
              "points": "90"
            }
          ]
        }
      ]
    },
    {
      "title": "LEADER",
      "entries": [
        {
          "type": "list",
          "items": [
            "Assault Intercessor Squad",
            "Bladeguard Veteran Squad",
            "Company Heroes",
            "Hellblaster Squad",
            "Infernus Squad",
            "Intercessor Squad",
            "Sternguard Veteran Squad",
            "Victrix Honour Guard",
            "Wardens of Ultramar",
            "Crusader Squad",
            "Sternguard Veteran Squad",
            "Sword Brethren Squad",
            "Inner Circle Companions",
            "Deathwatch Veterans",
            "Decimus Kill Team",
            "Fortis Kill Team",
            "Assault Squad",
            "Command Squad",
            "Vanguard Veteran Squad",
            "Wolf Guard"
          ]
        }
      ]
    }
  ],
  "exportSchemaVersion": 1,
  "parserVersion": "2026-03-19-durable-normalization-v1",
  "quality": {
    "rawSectionTitles": [
      "ABILITIES",
      "UNIT COMPOSITION",
      "LEADER"
    ],
    "exportedSectionTitles": [
      "ABILITIES",
      "UNIT COMPOSITION",
      "LEADER"
    ],
    "missingExpectedSections": [],
    "warnings": []
  }
}