{
  "source": {
    "url": "http://wahapedia.ru/wh40k10ed/factions/space-marines/Stormhawk-Interceptor",
    "faction_slug": "space-marines",
    "datasheet_slug": "Stormhawk-Interceptor",
    "output_slug": "ultramarines"
  },
  "name": "Stormhawk Interceptor",
  "base_size": "\u2300120 x 92mm flying base",
  "characteristics": {
    "M": "20+\"",
    "T": "9",
    "Sv": "3+",
    "W": "10",
    "Ld": "6+",
    "OC": "0"
  },
  "weapons": {
    "ranged_weapons": [
      {
        "name": "Icarus stormcannon",
        "abilities": [
          "anti-fly 2+"
        ],
        "range": "48\"",
        "a": "6",
        "bs": "3+",
        "s": "7",
        "ap": "-1",
        "d": "2"
      },
      {
        "name": "Las-talon",
        "abilities": [],
        "range": "36\"",
        "a": "2",
        "bs": "3+",
        "s": "10",
        "ap": "-3",
        "d": "D6+1"
      },
      {
        "name": "Skyhammer missile launcher",
        "abilities": [
          "anti-fly 2+"
        ],
        "range": "48\"",
        "a": "3",
        "bs": "3+",
        "s": "8",
        "ap": "-1",
        "d": "D3"
      },
      {
        "name": "Twin assault cannon",
        "abilities": [
          "devastating wounds",
          "twin-linked"
        ],
        "range": "24\"",
        "a": "6",
        "bs": "3+",
        "s": "6",
        "ap": "0",
        "d": "1"
      },
      {
        "name": "Twin heavy bolter",
        "abilities": [
          "sustained hits 1",
          "twin-linked"
        ],
        "range": "36\"",
        "a": "3",
        "bs": "3+",
        "s": "5",
        "ap": "-1",
        "d": "2"
      },
      {
        "name": "Typhoon missile launcher \u2013 frag",
        "abilities": [
          "blast"
        ],
        "range": "48\"",
        "a": "2D6",
        "bs": "3+",
        "s": "4",
        "ap": "0",
        "d": "1"
      },
      {
        "name": "Typhoon missile launcher \u2013 krak",
        "abilities": [],
        "range": "48\"",
        "a": "2",
        "bs": "3+",
        "s": "9",
        "ap": "-2",
        "d": "D6"
      }
    ],
    "melee_weapons": [
      {
        "name": "Armoured hull",
        "abilities": [],
        "range": "Melee",
        "a": "3",
        "ws": "4+",
        "s": "6",
        "ap": "0",
        "d": "1"
      }
    ]
  },
  "abilities": {
    "core": [
      "Deadly Demise D3"
    ],
    "faction": [
      "Oath of Moment"
    ],
    "datasheet": [
      {
        "type": "rule",
        "text": "Each time this model makes a ranged attack that targets a unit that can Fly , add 1 to the Hit roll .",
        "name": "Interceptor"
      }
    ],
    "other": []
  },
  "unit_composition": [
    {
      "type": "list",
      "items": [
        "1 Stormhawk Interceptor"
      ]
    },
    {
      "type": "statement",
      "text": "twin assault cannon; skyhammer missile launcher; las-talon; armoured hull.",
      "label": "This model is equipped with"
    },
    {
      "type": "points",
      "rows": [
        {
          "label": "1 model",
          "points": "155"
        }
      ]
    }
  ],
  "keywords": [
    "VEHICLE",
    "FLY",
    "AIRCRAFT",
    "IMPERIUM",
    "SMOKE",
    "STORMHAWK INTERCEPTOR",
    "RAVENWING"
  ],
  "faction_keywords": [
    "ADEPTUS ASTARTES"
  ],
  "sections": [
    {
      "title": "ABILITIES",
      "entries": [
        {
          "type": "tagged_list",
          "label": "CORE",
          "items": [
            "Deadly Demise D3"
          ]
        },
        {
          "type": "tagged_list",
          "label": "FACTION",
          "items": [
            "Oath of Moment"
          ]
        },
        {
          "type": "rule",
          "text": "Each time this model makes a ranged attack that targets a unit that can Fly , add 1 to the Hit roll .",
          "name": "Interceptor"
        }
      ]
    },
    {
      "title": "UNIT COMPOSITION",
      "entries": [
        {
          "type": "list",
          "items": [
            "1 Stormhawk Interceptor"
          ]
        },
        {
          "type": "statement",
          "text": "twin assault cannon; skyhammer missile launcher; las-talon; armoured hull.",
          "label": "This model is equipped with"
        },
        {
          "type": "points",
          "rows": [
            {
              "label": "1 model",
              "points": "155"
            }
          ]
        }
      ]
    }
  ]
}