{
  "exportSchemaVersion": 1,
  "parserVersion": "2026-03-20-builder-fidelity-v2",
  "source": {
    "url": "http://wahapedia.ru/wh40k10ed/factions/t-au-empire/Remote-Sensor-Tower",
    "normalizedUrl": "http://wahapedia.ru/wh40k10ed/factions/t-au-empire/Remote-Sensor-Tower",
    "canonicalSourceId": "wahapedia:6941c0719e67a60b335a2ace154c2522bccf2c77",
    "faction_slug": "t-au-empire",
    "datasheet_slug": "Remote-Sensor-Tower",
    "fetchedAt": "2026-04-20T20:50:00+00:00",
    "contentHash": "fc1af1f088d6c4bd9062214b3480cad2f7da50c7740994ffa960e560353bdcac",
    "output_slug": "t-au-empire"
  },
  "name": "Remote Sensor Tower",
  "base_size": "\u2300Use model",
  "characteristics": {
    "M": "-",
    "T": "8",
    "Sv": "4+",
    "W": "4",
    "Ld": "8+",
    "OC": "0"
  },
  "weapons": {},
  "abilities": {
    "core": [],
    "faction": [],
    "datasheet": [
      {
        "type": "rule",
        "text": "While a friendly T\u2019AU EMPIRE unit is within 6\" of this FORTIFICATION , each time you target that unit with a Stratagem , roll one D6: on a 5+, you gain 1CP.",
        "name": "Orbital Comms Array (Aura)"
      },
      {
        "type": "rule",
        "text": "Each time a ranged attack is allocated to a model, if that model is not fully visible to every model in the attacking unit because of this FORTIFICATION , that model has the Benefit of Cover against that attack.",
        "name": "Reinforced Cover"
      },
      {
        "type": "rule",
        "text": "While an enemy unit is only within Engagement Range of one or more FORTIFICATIONS from your army:",
        "name": "Fortification"
      }
    ],
    "other": [
      {
        "type": "list",
        "items": [
          "That unit can still be selected as the target of ranged attacks, but each time such an attack is made, unless it is made with a Pistol , subtract 1 from the Hit roll .",
          "Models in that unit do not need to take Desperate Escape tests due to Falling Back while Battle-shocked , except for those that will move over enemy models when doing so."
        ]
      }
    ]
  },
  "unit_composition": [
    {
      "type": "list",
      "items": [
        "1 Remote Sensor Tower"
      ]
    },
    {
      "type": "statement",
      "text": "nothing.",
      "label": "This model is equipped with"
    },
    {
      "type": "points",
      "rows": [
        {
          "label": "1 model",
          "points": "50"
        }
      ]
    }
  ],
  "keywords": [
    "FORTIFICATION",
    "REMOTE SENSOR TOWER"
  ],
  "faction_keywords": [
    "T\u2019AU EMPIRE"
  ],
  "sections": [
    {
      "title": "ABILITIES",
      "entries": [
        {
          "type": "rule",
          "text": "While a friendly T\u2019AU EMPIRE unit is within 6\" of this FORTIFICATION , each time you target that unit with a Stratagem , roll one D6: on a 5+, you gain 1CP.",
          "name": "Orbital Comms Array (Aura)"
        },
        {
          "type": "rule",
          "text": "Each time a ranged attack is allocated to a model, if that model is not fully visible to every model in the attacking unit because of this FORTIFICATION , that model has the Benefit of Cover against that attack.",
          "name": "Reinforced Cover"
        },
        {
          "type": "rule",
          "text": "While an enemy unit is only within Engagement Range of one or more FORTIFICATIONS from your army:",
          "name": "Fortification"
        },
        {
          "type": "list",
          "items": [
            "That unit can still be selected as the target of ranged attacks, but each time such an attack is made, unless it is made with a Pistol , subtract 1 from the Hit roll .",
            "Models in that unit do not need to take Desperate Escape tests due to Falling Back while Battle-shocked , except for those that will move over enemy models when doing so."
          ]
        }
      ]
    },
    {
      "title": "UNIT COMPOSITION",
      "entries": [
        {
          "type": "list",
          "items": [
            "1 Remote Sensor Tower"
          ]
        },
        {
          "type": "statement",
          "text": "nothing.",
          "label": "This model is equipped with"
        },
        {
          "type": "points",
          "rows": [
            {
              "label": "1 model",
              "points": "50"
            }
          ]
        }
      ]
    }
  ],
  "quality": {
    "rawSectionTitles": [
      "ABILITIES",
      "UNIT COMPOSITION"
    ],
    "exportedSectionTitles": [
      "ABILITIES",
      "UNIT COMPOSITION"
    ],
    "missingExpectedSections": [],
    "warnings": [],
    "keywordColumnCount": 2
  }
}